{"version": 0.6, "generator": "Overpass API 0.7.61.5 4133829e", "osm3s": {"timestamp_osm_base": "2024-02-25T09:09:08Z", "copyright": "The data included in this document is from www.openstreetmap.org. The data is made available under ODbL."}, "elements": [{"type": "node", "id": 5565408323, "lat": 23.1784282, "lon": 72.5725415}, {"type": "node", "id": 5565408324, "lat": 23.1780731, "lon": 72.572292}, {"type": "node", "id": 5565408325, "lat": 23.1784763, "lon": 72.571647}, {"type": "node", "id": 5565408326, "lat": 23.1787487, "lon": 72.5718387}, {"type": "node", "id": 5565408327, "lat": 23.1786822, "lon": 72.5719366}, {"type": "node", "id": 5565408328, "lat": 23.1787808, "lon": 72.5720064}, {"type": "way", "id": 581725472, "nodes": [5565408323, 5565408324, 5565408325, 5565408326, 5565408327, 5565408328, 5565408323], "tags": {"building": "temple"}}]}